CHANGES.txt
COPYRIGHT.txt
LICENSE.txt
README.txt
setup.cfg
setup.py
repoze/__init__.py
repoze.bfg.mako.egg-info/PKG-INFO
repoze.bfg.mako.egg-info/SOURCES.txt
repoze.bfg.mako.egg-info/dependency_links.txt
repoze.bfg.mako.egg-info/entry_points.txt
repoze.bfg.mako.egg-info/namespace_packages.txt
repoze.bfg.mako.egg-info/not-zip-safe
repoze.bfg.mako.egg-info/requires.txt
repoze.bfg.mako.egg-info/top_level.txt
repoze/bfg/__init__.py
repoze/bfg/mako/__init__.py
repoze/bfg/mako/configure.zcml
repoze/bfg/mako/paster.py
repoze/bfg/mako/paster_template/+project+.ini_tmpl
repoze/bfg/mako/paster_template/CHANGES.txt_tmpl
repoze/bfg/mako/paster_template/README.txt_tmpl
repoze/bfg/mako/paster_template/setup.py_tmpl
repoze/bfg/mako/paster_template/+package+/__init__.py
repoze/bfg/mako/paster_template/+package+/configure.zcml
repoze/bfg/mako/paster_template/+package+/tests.py_tmpl
repoze/bfg/mako/paster_template/+package+/views.py_tmpl
repoze/bfg/mako/paster_template/+package+/templates/mytemplate.mak
repoze/bfg/mako/paster_template/+package+/templates/static/default.css
repoze/bfg/mako/paster_template/+package+/templates/static/templatelicense.txt
repoze/bfg/mako/paster_template/+package+/templates/static/images/img01.gif
repoze/bfg/mako/paster_template/+package+/templates/static/images/img02.gif
repoze/bfg/mako/paster_template/+package+/templates/static/images/img03.gif
repoze/bfg/mako/paster_template/+package+/templates/static/images/img04.gif
repoze/bfg/mako/paster_template/+package+/templates/static/images/spacer.gif
repoze/bfg/mako/tests/__init__.py
repoze/bfg/mako/tests/test_it.py
repoze/bfg/mako/tests/templates/helloworld.mak
repoze/bfg/mako/tests/templates/helloworld.mako