Metadata-Version: 1.0
Name: repoze.bfg.mako
Version: 0.3
Summary: Mako template bindings for repoze.bfg
Home-page: http://www.repoze.org
Author: Chris McDonough / Agendaless Consulting
Author-email: repoze-dev@lists.repoze.org
License: BSD-derived (http://www.repoze.org/LICENSE.txt)
Keywords: web wsgi zope
Platform: UNKNOWN
Classifier: Intended Audience :: Developers
Classifier: Programming Language :: Python
Classifier: Framework :: BFG
Classifier: License :: Repoze Public License
